[
  {
    "processingOrder": 8,
    "startTime": "Sample Text",
    "endTime": "Sample Text",
    "status": "Sample Text",
    "fusionRequestId": 9206290,
    "jobDefinitionName": "Sample Text",
    "soapId": 5916603,
    "runNumber": 63,
    "instanceId": 3239908,
    "fileId": 3299281,
    "statementId": 7229332,
    "buId": 7971238,
    "seqId": 1220564,
    "selectInConcProcessing": false,
    "requestType": "Sample Text",
    "requestResult": "Sample Text",
    "requestMessage": "Sample Text",
    "resultDocId": 4308203,
    "userId": 4001407,
    "jobType": "Sample Text",
    "jobPackageName": "Sample Text",
    "ucmLoadFileName": "Sample Text",
    "workerId": 8019662,
    "subGroupId": 7778589,
    "errorAction": "Sample Text",
    "customWsdl": "Sample Text",
    "response": "Sample Text",
    "retryCounter": 63,
    "statement": "Sample Text"
  },
  {
    "processingOrder": 48,
    "startTime": "Sample Text",
    "endTime": "Sample Text",
    "status": "Sample Text",
    "fusionRequestId": 8988341,
    "jobDefinitionName": "Sample Text",
    "soapId": 5680466,
    "runNumber": 50,
    "instanceId": 4778484,
    "fileId": 2436185,
    "statementId": 9335981,
    "buId": 9899360,
    "seqId": 4587205,
    "selectInConcProcessing": false,
    "requestType": "Sample Text",
    "requestResult": "Sample Text",
    "requestMessage": "Sample Text",
    "resultDocId": 5365649,
    "userId": 1056071,
    "jobType": "Sample Text",
    "jobPackageName": "Sample Text",
    "ucmLoadFileName": "Sample Text",
    "workerId": 8504411,
    "subGroupId": 1455919,
    "errorAction": "Sample Text",
    "customWsdl": "Sample Text",
    "response": "Sample Text",
    "retryCounter": 9,
    "statement": "Sample Text"
  },
  {
    "processingOrder": 26,
    "startTime": "Sample Text",
    "endTime": "Sample Text",
    "status": "Sample Text",
    "fusionRequestId": 7257931,
    "jobDefinitionName": "Sample Text",
    "soapId": 1137865,
    "runNumber": 34,
    "instanceId": 3747309,
    "fileId": 1355110,
    "statementId": 3823772,
    "buId": 9572089,
    "seqId": 6326878,
    "selectInConcProcessing": false,
    "requestType": "Sample Text",
    "requestResult": "Sample Text",
    "requestMessage": "Sample Text",
    "resultDocId": 2909980,
    "userId": 5009736,
    "jobType": "Sample Text",
    "jobPackageName": "Sample Text",
    "ucmLoadFileName": "Sample Text",
    "workerId": 9471097,
    "subGroupId": 8142346,
    "errorAction": "Sample Text",
    "customWsdl": "Sample Text",
    "response": "Sample Text",
    "retryCounter": 12,
    "statement": "Sample Text"
  }
]
